customer_analisis.py
customer_analisis_elf_unic-0.1.0.dist-info/METADATA
customer_analisis_elf_unic-0.1.0.dist-info/WHEEL
customer_analisis_elf_unic-0.1.0.dist-info/entry_points.txt
customer_analisis_elf_unic-0.1.0.dist-info/top_level.txt
customer_analisis_elf_unic-0.1.0.dist-info/RECORD
