Metadata-Version: 2.1
Name: customer_analisis_elf_unic
Version: 0.1.0
Summary: analise customers
Author: Varvara
Requires-Python: >=3.8
Requires-Dist: pandas==2.2.3
